realtimex_lead_search/__init__.py
realtimex_lead_search/lead_search_agent.py
realtimex_lead_search/lead_search/__init__.py
realtimex_lead_search/lead_search/anti_detection.py
realtimex_lead_search/lead_search/lead_cache_manager.py
realtimex_lead_search/lead_search/lead_data_manager.py
realtimex_lead_search/lead_search/lead_extractor.py
realtimex_lead_search/lead_search/lead_scorer.py
realtimex_lead_search/lead_search/llm_adapter.py
realtimex_lead_search/lead_search/location_normalizer.py
realtimex_lead_search/lead_search/models.py
realtimex_lead_search/lead_search/playwright_scraper.py
realtimex_lead_search/lead_search/prompts.py
realtimex_lead_search/lead_search/search_strategies.py
realtimex_lead_search-0.2.0.dist-info/METADATA
realtimex_lead_search-0.2.0.dist-info/WHEEL
realtimex_lead_search-0.2.0.dist-info/RECORD
