Metadata-Version: 2.4
Name: realtimex-lead-search
Version: 0.2.0
Summary: Lead search helper for RealtimeX flows.
Author-email: RealtimeX <dev@realtimex.com>
Requires-Python: >=3.10
Provides-Extra: dev
Requires-Dist: build; extra == 'dev'
Requires-Dist: pytest-cov>=4.1.0; extra == 'dev'
Requires-Dist: pytest>=7.4.0; extra == 'dev'
Requires-Dist: twine; extra == 'dev'
Provides-Extra: playwright
Requires-Dist: playwright>=1.56.0; extra == 'playwright'
